{
  "id": "17783",
  "name": "Architecture of collaborative software tools",
  "numComments": 0,
  "comments": [],
  "public": true,
  "type": "project",
  "updated_at": "2017-02-10T18:59:30.220Z",
  "user_id": "13687",
  "voter_ids": [],
  "created_at": "2016-02-05T18:34:11.877Z",
  "description": "<p>Core Intention: Documentation of existing software tools that together will be able to create an eco-system of infrastructure for solidarity economy groups.<p><p>Suggested output:</p>\n<ol>\n<li>Architectural diagram of existing software available for solidarity groups to use.</li>\n<li>Detail on each piece of software included, filterable.</li>\n</ol>\n<p>Goals:</p>\n<ol>\n<li>Solidarity groups working for change on the ground could use this as input to assembling software infrastructure needed for their group.</li>\n<li>Software developers can determine where there is overlap and thus opportunity for collaboration; where there are gaps and thus opportunity for new useful software; and where interoperability would be most useful so that it can be developed.</li>\n</ol>\n",
  "communities": [
    {
      "avatar_url": "https://d3ngex8q79bk55.cloudfront.net/community/1222/avatar/1451885428347_CTASeal-40.png",
      "banner_url": "https://d3ngex8q79bk55.cloudfront.net/community/1222/banner/1454643618118_5.9.14_HyloLandingPageHexagonTextureBlue.jpg",
      "id": "1222",
      "name": "Collaborative Technology Alliance",
      "slug": "collaborative-technology-alliance"
    }
  ],
  "community_ids": [
    "1222"
  ],
  "follower_ids": [
    "23845",
    "18556",
    "13414",
    "15961",
    "16353",
    "19295",
    "18341",
    "9104",
    "16937",
    "18639",
    "9541",
    "10185",
    "17164",
    "17094",
    "982",
    "15106",
    "5522",
    "10984"
  ],
  "people": [
    {
      "avatar_url": "https://media.licdn.com/mpr/mprx/0_sMe3tizezAMua5TAssWYtT5Fzzg826TAqjyYt8NJoPWK1Cnl9xZDphhcR4jx738jUsE0gF6Iq2yn",
      "id": "23845",
      "name": "Jim Whitescarver"
    },
    {
      "avatar_url": "https://media.licdn.com/mpr/mprx/0_PDVbcGjsm_ACGI9GndGFyTCUI-ECboLCxDCdlBsso9Bibska0Dh6yPBsWqbiGIVi9dmbJXZVCvb_TmKCxY0U09z9FvbGTmhaxY0kqchR2NtmwZRt1fWoN_aobhg-HmB09jUwP59hI9U",
      "id": "18556",
      "name": "Ralph Boeije"
    },
    {
      "avatar_url": "https://graph.facebook.com/10154084058892783/picture?type=large",
      "id": "13414",
      "name": "Victor Vorski"
    },
    {
      "avatar_url": "https://d3ngex8q79bk55.cloudfront.net/user/15961/avatar/1447927440956_Lucas-im-Kreis-swkorr.png",
      "id": "15961",
      "name": "Lucas Huber"
    },
    {
      "avatar_url": "https://www.gravatar.com/avatar/92952ae3ef39a8d687b730b7a743fac4?d=mm&s=140",
      "id": "16353",
      "name": "James Gien Wong"
    },
    {
      "avatar_url": "https://www.gravatar.com/avatar/473847c8612ca5aa63907b13b51514be?d=mm&s=140",
      "id": "19295",
      "name": "Paul Free"
    },
    {
      "avatar_url": "https://d3ngex8q79bk55.cloudfront.net/user/18341/avatar/1457540175531_10201618169513771.jpg",
      "id": "18341",
      "name": "john gieryn"
    },
    {
      "avatar_url": "https://www.gravatar.com/avatar/64cc0de06809f3ecffd3a4ff0794944b?d=mm&s=140",
      "id": "9104",
      "name": "miles thompson"
    },
    {
      "avatar_url": "https://www.gravatar.com/avatar/976478b94397209d9d2fe55e20b7eb29?d=mm&s=140",
      "id": "16937",
      "name": "A. Renato"
    },
    {
      "avatar_url": "https://d3ngex8q79bk55.cloudfront.net/user/18639/avatar/1458884014802_timbild.jpg",
      "id": "18639",
      "name": "Tim Sandgren"
    },
    {
      "avatar_url": "https://lh5.googleusercontent.com/-B7xWA1ufUVo/AAAAAAAAAAI/AAAAAAAAIvI/IuJPP09WTKs/photo.jpg",
      "id": "9541",
      "name": "Jacob Gadikian"
    },
    {
      "avatar_url": "https://lh6.googleusercontent.com/-6qCmNicVAwk/AAAAAAAAAAI/AAAAAAAABjU/zocYh5ltvhg/photo.jpg",
      "id": "10185",
      "name": "Tammy Lea Meyer"
    },
    {
      "avatar_url": "https://www.gravatar.com/avatar/7b33f331abeafc9583e4815a6ee58733?d=mm&s=140",
      "id": "17164",
      "name": "Kei Kreutler"
    },
    {
      "avatar_url": "https://www.gravatar.com/avatar/9b6e88ae1f9f7a10ce0bd7f687a8f931?d=mm&s=140",
      "id": "17094",
      "name": "Aaron Wolf"
    },
    {
      "avatar_url": "https://lh6.googleusercontent.com/-Yykp9BrS5pM/AAAAAAAAAAI/AAAAAAAAGFQ/45VGI9GhQCQ/photo.jpg",
      "id": "982",
      "name": "Connor Turland"
    },
    {
      "avatar_url": "https://www.gravatar.com/avatar/57d4c58d479214c2964a4fb6fa6387e8?d=mm&s=140",
      "id": "15106",
      "name": "Greg Cassel"
    },
    {
      "avatar_url": "https://lh5.googleusercontent.com/-l9LseXfBY9U/AAAAAAAAAAI/AAAAAAAAAAA/8mBqsqXBhoE/photo.jpg",
      "id": "5522",
      "name": "Bob Haugen"
    },
    {
      "avatar_url": "https://lh6.googleusercontent.com/-AaMnZLck16E/AAAAAAAAAAI/AAAAAAAAABI/bkaMU3WvoY8/photo.jpg",
      "id": "10984",
      "name": "François Beauregard"
    },
    {
      "avatar_url": "https://d3ngex8q79bk55.cloudfront.net/user/13687/avatar/1455652393490_fosterlynn.png",
      "bio": null,
      "id": "13687",
      "name": "Lynn Foster"
    }
  ]
}